{
	"version": "5",
	"dialect": "mysql",
	"id": "244b5542-c302-43ea-b2a5-3bb43f896740",
	"prevId": "00000000-0000-0000-0000-000000000000",
	"tables": {
		"articles": {
			"name": "articles",
			"columns": {
				"id": {
					"name": "id",
					"type": "bigint",
					"primaryKey": false,
					"notNull": true,
					"autoincrement": true
				},
				"title": {
					"name": "title",
					"type": "varchar(255)",
					"primaryKey": false,
					"notNull": false,
					"autoincrement": false
				},
				"short_description": {
					"name": "short_description",
					"type": "varchar(255)",
					"primaryKey": false,
					"notNull": false,
					"autoincrement": false
				},
				"description": {
					"name": "description",
					"type": "text",
					"primaryKey": false,
					"notNull": false,
					"autoincrement": false
				},
				"created_at": {
					"name": "created_at",
					"type": "timestamp",
					"primaryKey": false,
					"notNull": true,
					"autoincrement": false,
					"default": "(now())"
				},
				"updated_at": {
					"name": "updated_at",
					"type": "timestamp",
					"primaryKey": false,
					"notNull": true,
					"autoincrement": false,
					"onUpdate": true,
					"default": "(now())"
				}
			},
			"indexes": {},
			"foreignKeys": {},
			"compositePrimaryKeys": {
				"articles_id": {
					"name": "articles_id",
					"columns": ["id"]
				}
			},
			"uniqueConstraints": {}
		},
		"comments": {
			"name": "comments",
			"columns": {
				"id": {
					"name": "id",
					"type": "bigint",
					"primaryKey": false,
					"notNull": true,
					"autoincrement": true
				},
				"content": {
					"name": "content",
					"type": "text",
					"primaryKey": false,
					"notNull": false,
					"autoincrement": false
				},
				"article_id": {
					"name": "article_id",
					"type": "bigint",
					"primaryKey": false,
					"notNull": true,
					"autoincrement": false
				},
				"created_at": {
					"name": "created_at",
					"type": "timestamp",
					"primaryKey": false,
					"notNull": true,
					"autoincrement": false,
					"default": "(now())"
				},
				"updated_at": {
					"name": "updated_at",
					"type": "timestamp",
					"primaryKey": false,
					"notNull": true,
					"autoincrement": false,
					"onUpdate": true,
					"default": "(now())"
				}
			},
			"indexes": {},
			"foreignKeys": {},
			"compositePrimaryKeys": {
				"comments_id": {
					"name": "comments_id",
					"columns": ["id"]
				}
			},
			"uniqueConstraints": {}
		},
		"jwt_denylists": {
			"name": "jwt_denylists",
			"columns": {
				"id": {
					"name": "id",
					"type": "bigint",
					"primaryKey": false,
					"notNull": true,
					"autoincrement": true
				},
				"jti": {
					"name": "jti",
					"type": "varchar(255)",
					"primaryKey": false,
					"notNull": true,
					"autoincrement": false
				},
				"exp": {
					"name": "exp",
					"type": "timestamp",
					"primaryKey": false,
					"notNull": true,
					"autoincrement": false
				},
				"created_at": {
					"name": "created_at",
					"type": "timestamp",
					"primaryKey": false,
					"notNull": true,
					"autoincrement": false,
					"default": "(now())"
				},
				"updated_at": {
					"name": "updated_at",
					"type": "timestamp",
					"primaryKey": false,
					"notNull": true,
					"autoincrement": false,
					"onUpdate": true,
					"default": "(now())"
				}
			},
			"indexes": {},
			"foreignKeys": {},
			"compositePrimaryKeys": {
				"jwt_denylists_id": {
					"name": "jwt_denylists_id",
					"columns": ["id"]
				}
			},
			"uniqueConstraints": {}
		},
		"likes": {
			"name": "likes",
			"columns": {
				"id": {
					"name": "id",
					"type": "bigint",
					"primaryKey": false,
					"notNull": true,
					"autoincrement": true
				},
				"likes": {
					"name": "likes",
					"type": "int",
					"primaryKey": false,
					"notNull": false,
					"autoincrement": false
				},
				"dislikes": {
					"name": "dislikes",
					"type": "int",
					"primaryKey": false,
					"notNull": false,
					"autoincrement": false
				},
				"likeable_type": {
					"name": "likeable_type",
					"type": "varchar(255)",
					"primaryKey": false,
					"notNull": true,
					"autoincrement": false
				},
				"likeable_id": {
					"name": "likeable_id",
					"type": "bigint",
					"primaryKey": false,
					"notNull": true,
					"autoincrement": false
				},
				"created_at": {
					"name": "created_at",
					"type": "timestamp",
					"primaryKey": false,
					"notNull": true,
					"autoincrement": false,
					"default": "(now())"
				},
				"updated_at": {
					"name": "updated_at",
					"type": "timestamp",
					"primaryKey": false,
					"notNull": true,
					"autoincrement": false,
					"onUpdate": true,
					"default": "(now())"
				}
			},
			"indexes": {},
			"foreignKeys": {},
			"compositePrimaryKeys": {
				"likes_id": {
					"name": "likes_id",
					"columns": ["id"]
				}
			},
			"uniqueConstraints": {}
		},
		"users": {
			"name": "users",
			"columns": {
				"id": {
					"name": "id",
					"type": "bigint",
					"primaryKey": false,
					"notNull": true,
					"autoincrement": true
				},
				"email": {
					"name": "email",
					"type": "varchar(255)",
					"primaryKey": false,
					"notNull": true,
					"autoincrement": false
				},
				"encrypted_password": {
					"name": "encrypted_password",
					"type": "varchar(255)",
					"primaryKey": false,
					"notNull": true,
					"autoincrement": false
				},
				"reset_password_token": {
					"name": "reset_password_token",
					"type": "varchar(255)",
					"primaryKey": false,
					"notNull": false,
					"autoincrement": false
				},
				"reset_password_sent_at": {
					"name": "reset_password_sent_at",
					"type": "timestamp",
					"primaryKey": false,
					"notNull": false,
					"autoincrement": false
				},
				"remember_created_at": {
					"name": "remember_created_at",
					"type": "timestamp",
					"primaryKey": false,
					"notNull": false,
					"autoincrement": false
				},
				"created_at": {
					"name": "created_at",
					"type": "timestamp",
					"primaryKey": false,
					"notNull": true,
					"autoincrement": false,
					"default": "(now())"
				},
				"updated_at": {
					"name": "updated_at",
					"type": "timestamp",
					"primaryKey": false,
					"notNull": true,
					"autoincrement": false,
					"onUpdate": true,
					"default": "(now())"
				}
			},
			"indexes": {},
			"foreignKeys": {},
			"compositePrimaryKeys": {
				"users_id": {
					"name": "users_id",
					"columns": ["id"]
				}
			},
			"uniqueConstraints": {
				"users_email_unique": {
					"name": "users_email_unique",
					"columns": ["email"]
				}
			}
		}
	},
	"schemas": {},
	"_meta": {
		"schemas": {},
		"tables": {},
		"columns": {}
	}
}
